odoo10_addon_account_banking_pain_base-10.0.1.1.3-nspkg.pth
odoo/addons/account_banking_pain_base/README.rst
odoo/addons/account_banking_pain_base/__init__.py
odoo/addons/account_banking_pain_base/__manifest__.py
odoo/addons/account_banking_pain_base/post_install.py
odoo/addons/account_banking_pain_base/i18n/account_banking_pain_base.pot
odoo/addons/account_banking_pain_base/i18n/da_DK.po
odoo/addons/account_banking_pain_base/i18n/de.po
odoo/addons/account_banking_pain_base/i18n/es.po
odoo/addons/account_banking_pain_base/i18n/fr.po
odoo/addons/account_banking_pain_base/i18n/hr.po
odoo/addons/account_banking_pain_base/i18n/nb_NO.po
odoo/addons/account_banking_pain_base/i18n/nl.po
odoo/addons/account_banking_pain_base/i18n/nl_NL.po
odoo/addons/account_banking_pain_base/i18n/pt.po
odoo/addons/account_banking_pain_base/i18n/pt_BR.po
odoo/addons/account_banking_pain_base/i18n/sl.po
odoo/addons/account_banking_pain_base/models/__init__.py
odoo/addons/account_banking_pain_base/models/account_config_settings.py
odoo/addons/account_banking_pain_base/models/account_payment_line.py
odoo/addons/account_banking_pain_base/models/account_payment_method.py
odoo/addons/account_banking_pain_base/models/account_payment_mode.py
odoo/addons/account_banking_pain_base/models/account_payment_order.py
odoo/addons/account_banking_pain_base/models/bank_payment_line.py
odoo/addons/account_banking_pain_base/models/res_company.py
odoo/addons/account_banking_pain_base/security/security.xml
odoo/addons/account_banking_pain_base/static/description/icon.png
odoo/addons/account_banking_pain_base/views/account_config_settings.xml
odoo/addons/account_banking_pain_base/views/account_payment_line.xml
odoo/addons/account_banking_pain_base/views/account_payment_method.xml
odoo/addons/account_banking_pain_base/views/account_payment_mode.xml
odoo/addons/account_banking_pain_base/views/account_payment_order.xml
odoo/addons/account_banking_pain_base/views/bank_payment_line_view.xml
odoo10_addon_account_banking_pain_base-10.0.1.1.3.dist-info/METADATA
odoo10_addon_account_banking_pain_base-10.0.1.1.3.dist-info/WHEEL
odoo10_addon_account_banking_pain_base-10.0.1.1.3.dist-info/namespace_packages.txt
odoo10_addon_account_banking_pain_base-10.0.1.1.3.dist-info/top_level.txt
odoo10_addon_account_banking_pain_base-10.0.1.1.3.dist-info/RECORD
