Metadata-Version: 2.1
Name: odoo10-addon-account-banking-pain-base
Version: 10.0.1.1.3
Summary: Base module for PAIN file generation
Home-page: https://github.com/OCA/bank-payment
Author: Akretion, Noviat, Tecnativa, Odoo Community Association (OCA)
Author-email: support@odoo-community.org
License: AGPL-3
Platform: UNKNOWN
Classifier: Programming Language :: Python
Classifier: Framework :: Odoo
Classifier: License :: OSI Approved :: GNU Affero General Public License v3
Requires-Python: ~=2.7
Requires-Dist: lxml
Requires-Dist: odoo10-addon-account-payment-order
Requires-Dist: odoo (<10.1dev,>=10.0)
Requires-Dist: unidecode
